tornado_data_uri
