Metadata-Version: 1.0
Name: tornado-data-uri
Version: 0.0.2
Summary: Tornado Data-URI Encoder Template Tag
Home-page: UNKNOWN
Author: Shane R. Spencer
Author-email: shane@bogomip.com
License: MIT
Platform: UNKNOWN
